{
  "alpha": 0.42,
  "bias_num": {
    "1": 0.9829163906109714,
    "3": 0.7584925285491217,
    "4": 0.7077266308317672,
    "5": 0.35372085870417663,
    "8": 0.8015225408732511,
    "10": 0.7195166717068902,
    "11": 0.8387183140546525,
    "12": 1.0,
    "14": 0.5098546463982608,
    "17": 0.37783669879705156,
    "19": 0.8086742098691357,
    "20": 0.4976911518132364,
    "22": 0.8026687364412837,
    "24": 0.5426197037988213,
    "25": 0.8949529223212523,
    "6": 0.5018229081131248,
    "7": 0.7708933601076089,
    "15": 0.8206423203998361,
    "23": 0.530526156546988,
    "9": 0.3572184339108438,
    "13": 0.2592245767792188,
    "16": 0.7555142990134375,
    "21": 0.8697778498436872,
    "2": 0.8276730649132941,
    "18": 0.7055003446629027
  },
  "history": [
    [
      1,
      4,
      6,
      7,
      8,
      12,
      13,
      15,
      16,
      18,
      19,
      20,
      22,
      23,
      24
    ],
    [
      1,
      2,
      3,
      7,
      8,
      10,
      11,
      12,
      15,
      16,
      17,
      19,
      21,
      22,
      25
    ],
    [
      1,
      4,
      6,
      7,
      8,
      12,
      13,
      15,
      16,
      18,
      19,
      20,
      22,
      23,
      24
    ],
    [
      1,
      2,
      3,
      7,
      8,
      10,
      11,
      12,
      15,
      16,
      17,
      19,
      21,
      22,
      25
    ],
    [
      1,
      4,
      6,
      7,
      8,
      12,
      13,
      15,
      16,
      18,
      19,
      20,
      22,
      23,
      24
    ],
    [
      1,
      2,
      3,
      7,
      8,
      10,
      11,
      12,
      15,
      16,
      17,
      19,
      21,
      22,
      25
    ],
    [
      1,
      4,
      6,
      7,
      8,
      12,
      13,
      15,
      16,
      18,
      19,
      20,
      22,
      23,
      24
    ],
    [
      1,
      2,
      3,
      7,
      8,
      10,
      11,
      12,
      15,
      16,
      17,
      19,
      21,
      22,
      25
    ],
    [
      1,
      4,
      6,
      7,
      8,
      12,
      13,
      15,
      16,
      18,
      19,
      20,
      22,
      23,
      24
    ],
    [
      1,
      2,
      3,
      7,
      8,
      10,
      11,
      12,
      15,
      16,
      17,
      19,
      21,
      22,
      25
    ],
    [
      1,
      4,
      6,
      7,
      8,
      12,
      13,
      15,
      16,
      18,
      19,
      20,
      22,
      23,
      24
    ],
    [
      1,
      2,
      3,
      7,
      8,
      10,
      11,
      12,
      15,
      16,
      17,
      19,
      21,
      22,
      25
    ],
    [
      1,
      4,
      6,
      7,
      8,
      12,
      13,
      15,
      16,
      18,
      19,
      20,
      22,
      23,
      24
    ],
    [
      1,
      2,
      3,
      7,
      8,
      10,
      11,
      12,
      15,
      16,
      17,
      19,
      21,
      22,
      25
    ],
    [
      1,
      4,
      6,
      7,
      8,
      12,
      13,
      15,
      16,
      18,
      19,
      20,
      22,
      23,
      24
    ],
    [
      1,
      2,
      3,
      7,
      8,
      10,
      11,
      12,
      15,
      16,
      17,
      19,
      21,
      22,
      25
    ],
    [
      1,
      4,
      6,
      7,
      8,
      12,
      13,
      15,
      16,
      18,
      19,
      20,
      22,
      23,
      24
    ],
    [
      1,
      2,
      3,
      7,
      8,
      10,
      11,
      12,
      15,
      16,
      17,
      19,
      21,
      22,
      25
    ],
    [
      1,
      4,
      6,
      7,
      8,
      12,
      13,
      15,
      16,
      18,
      19,
      20,
      22,
      23,
      24
    ],
    [
      1,
      2,
      3,
      7,
      8,
      10,
      11,
      12,
      15,
      16,
      17,
      19,
      21,
      22,
      25
    ],
    [
      1,
      4,
      6,
      7,
      8,
      12,
      13,
      15,
      16,
      18,
      19,
      20,
      22,
      23,
      24
    ],
    [
      1,
      2,
      3,
      7,
      8,
      10,
      11,
      12,
      15,
      16,
      17,
      19,
      21,
      22,
      25
    ],
    [
      1,
      4,
      6,
      7,
      8,
      12,
      13,
      15,
      16,
      18,
      19,
      20,
      22,
      23,
      24
    ],
    [
      1,
      2,
      3,
      7,
      8,
      10,
      11,
      12,
      15,
      16,
      17,
      19,
      21,
      22,
      25
    ]
  ],
  "meta": {
    "lotes": [
      {
        "tag": "gerar",
        "qtd_apostas": 10,
        "base": [
          1,
          4,
          6,
          7,
          8,
          12,
          13,
          15,
          16,
          18,
          19,
          20,
          22,
          23,
          24
        ],
        "ts": "2025-12-02T10:07:32"
      },
      {
        "tag": "gerar",
        "qtd_apostas": 10,
        "base": [
          1,
          4,
          6,
          7,
          8,
          12,
          13,
          15,
          16,
          18,
          19,
          20,
          22,
          23,
          24
        ],
        "ts": "2025-12-02T10:08:35"
      },
      {
        "tag": "gerar",
        "qtd_apostas": 10,
        "base": [
          1,
          4,
          6,
          7,
          8,
          12,
          13,
          15,
          16,
          18,
          19,
          20,
          22,
          23,
          24
        ],
        "ts": "2025-12-02T10:09:13"
      },
      {
        "tag": "gerar",
        "qtd_apostas": 10,
        "base": [
          1,
          4,
          6,
          7,
          8,
          12,
          13,
          15,
          16,
          18,
          19,
          20,
          22,
          23,
          24
        ],
        "ts": "2025-12-02T10:09:34"
      },
      {
        "tag": "gerar",
        "qtd_apostas": 10,
        "base": [
          1,
          4,
          6,
          7,
          8,
          12,
          13,
          15,
          16,
          18,
          19,
          20,
          22,
          23,
          24
        ],
        "ts": "2025-12-02T10:09:58"
      },
      {
        "tag": "gerar",
        "qtd_apostas": 10,
        "base": [
          1,
          4,
          6,
          7,
          8,
          12,
          13,
          15,
          16,
          18,
          19,
          20,
          22,
          23,
          24
        ],
        "ts": "2025-12-02T10:10:22"
      },
      {
        "tag": "gerar",
        "qtd_apostas": 10,
        "base": [
          1,
          4,
          6,
          7,
          8,
          12,
          13,
          15,
          16,
          18,
          19,
          20,
          22,
          23,
          24
        ],
        "ts": "2025-12-02T10:10:52"
      },
      {
        "tag": "gerar",
        "qtd_apostas": 10,
        "base": [
          1,
          4,
          6,
          7,
          8,
          12,
          13,
          15,
          16,
          18,
          19,
          20,
          22,
          23,
          24
        ],
        "ts": "2025-12-02T10:11:08"
      },
      {
        "tag": "gerar",
        "qtd_apostas": 10,
        "base": [
          1,
          4,
          6,
          7,
          8,
          12,
          13,
          15,
          16,
          18,
          19,
          20,
          22,
          23,
          24
        ],
        "ts": "2025-12-02T10:11:29"
      },
      {
        "tag": "gerar",
        "qtd_apostas": 10,
        "base": [
          1,
          4,
          6,
          7,
          8,
          12,
          13,
          15,
          16,
          18,
          19,
          20,
          22,
          23,
          24
        ],
        "ts": "2025-12-02T10:11:52"
      },
      {
        "tag": "gerar",
        "qtd_apostas": 10,
        "base": [
          1,
          4,
          6,
          7,
          8,
          12,
          13,
          15,
          16,
          18,
          19,
          20,
          22,
          23,
          24
        ],
        "ts": "2025-12-02T18:20:27"
      },
      {
        "tag": "gerar",
        "qtd_apostas": 10,
        "base": [
          1,
          4,
          6,
          7,
          8,
          12,
          13,
          15,
          16,
          18,
          19,
          20,
          22,
          23,
          24
        ],
        "ts": "2025-12-02T18:21:04"
      }
    ],
    "aprendizado": [
      {
        "tag": "confirmar",
        "oficial": [
          1,
          2,
          3,
          7,
          8,
          10,
          11,
          12,
          15,
          16,
          17,
          19,
          21,
          22,
          25
        ],
        "placares": [
          10,
          10,
          10,
          9,
          8,
          8,
          10,
          10,
          9,
          8
        ],
        "melhor": 10,
        "media": 9.2,
        "topk": 10.0,
        "alpha_before": 0.36,
        "alpha_after": 0.36,
        "ts": "2025-12-02T10:08:23"
      },
      {
        "tag": "confirmar",
        "oficial": [
          1,
          2,
          3,
          7,
          8,
          10,
          11,
          12,
          15,
          16,
          17,
          19,
          21,
          22,
          25
        ],
        "placares": [
          7,
          10,
          9,
          12,
          10,
          9,
          9,
          8,
          9,
          8
        ],
        "melhor": 12,
        "media": 9.1,
        "topk": 10.666666666666666,
        "alpha_before": 0.36,
        "alpha_after": 0.3733333333333333,
        "ts": "2025-12-02T10:08:54"
      },
      {
        "tag": "confirmar",
        "oficial": [
          1,
          2,
          3,
          7,
          8,
          10,
          11,
          12,
          15,
          16,
          17,
          19,
          21,
          22,
          25
        ],
        "placares": [
          9,
          8,
          9,
          9,
          10,
          9,
          9,
          9,
          8,
          8
        ],
        "melhor": 10,
        "media": 8.8,
        "topk": 9.333333333333334,
        "alpha_before": 0.3733333333333333,
        "alpha_after": 0.36,
        "ts": "2025-12-02T10:09:19"
      },
      {
        "tag": "confirmar",
        "oficial": [
          1,
          2,
          3,
          7,
          8,
          10,
          11,
          12,
          15,
          16,
          17,
          19,
          21,
          22,
          25
        ],
        "placares": [
          9,
          10,
          9,
          6,
          10,
          8,
          9,
          12,
          10,
          8
        ],
        "melhor": 12,
        "media": 9.1,
        "topk": 10.666666666666666,
        "alpha_before": 0.36,
        "alpha_after": 0.3733333333333333,
        "ts": "2025-12-02T10:09:38"
      },
      {
        "tag": "confirmar",
        "oficial": [
          1,
          2,
          3,
          7,
          8,
          10,
          11,
          12,
          15,
          16,
          17,
          19,
          21,
          22,
          25
        ],
        "placares": [
          10,
          6,
          10,
          10,
          8,
          9,
          8,
          11,
          9,
          7
        ],
        "melhor": 11,
        "media": 8.8,
        "topk": 10.333333333333334,
        "alpha_before": 0.3733333333333333,
        "alpha_after": 0.37999999999999995,
        "ts": "2025-12-02T10:10:06"
      },
      {
        "tag": "confirmar",
        "oficial": [
          1,
          2,
          3,
          7,
          8,
          10,
          11,
          12,
          15,
          16,
          17,
          19,
          21,
          22,
          25
        ],
        "placares": [
          9,
          9,
          8,
          11,
          9,
          8,
          7,
          9,
          8,
          9
        ],
        "melhor": 11,
        "media": 8.7,
        "topk": 9.666666666666666,
        "alpha_before": 0.37999999999999995,
        "alpha_after": 0.3733333333333333,
        "ts": "2025-12-02T10:10:39"
      },
      {
        "tag": "confirmar",
        "oficial": [
          1,
          2,
          3,
          7,
          8,
          10,
          11,
          12,
          15,
          16,
          17,
          19,
          21,
          22,
          25
        ],
        "placares": [
          7,
          10,
          9,
          7,
          8,
          9,
          6,
          10,
          10,
          9
        ],
        "melhor": 10,
        "media": 8.5,
        "topk": 10.0,
        "alpha_before": 0.3733333333333333,
        "alpha_after": 0.3733333333333333,
        "ts": "2025-12-02T10:10:57"
      },
      {
        "tag": "confirmar",
        "oficial": [
          1,
          2,
          3,
          7,
          8,
          10,
          11,
          12,
          15,
          16,
          17,
          19,
          21,
          22,
          25
        ],
        "placares": [
          11,
          8,
          9,
          10,
          8,
          7,
          9,
          9,
          10,
          9
        ],
        "melhor": 11,
        "media": 9.0,
        "topk": 10.333333333333334,
        "alpha_before": 0.3733333333333333,
        "alpha_after": 0.37999999999999995,
        "ts": "2025-12-02T10:11:15"
      },
      {
        "tag": "confirmar",
        "oficial": [
          1,
          2,
          3,
          7,
          8,
          10,
          11,
          12,
          15,
          16,
          17,
          19,
          21,
          22,
          25
        ],
        "placares": [
          8,
          8,
          7,
          7,
          7,
          7,
          9,
          8,
          11,
          9
        ],
        "melhor": 11,
        "media": 8.1,
        "topk": 9.666666666666666,
        "alpha_before": 0.37999999999999995,
        "alpha_after": 0.3733333333333333,
        "ts": "2025-12-02T10:11:36"
      },
      {
        "tag": "confirmar",
        "oficial": [
          1,
          2,
          3,
          7,
          8,
          10,
          11,
          12,
          15,
          16,
          17,
          19,
          21,
          22,
          25
        ],
        "placares": [
          8,
          6,
          11,
          11,
          7,
          6,
          12,
          8,
          11,
          9
        ],
        "melhor": 12,
        "media": 8.9,
        "topk": 11.333333333333334,
        "alpha_before": 0.3733333333333333,
        "alpha_after": 0.39999999999999997,
        "ts": "2025-12-02T10:17:15"
      },
      {
        "tag": "confirmar",
        "oficial": [
          1,
          2,
          3,
          7,
          8,
          10,
          11,
          12,
          15,
          16,
          17,
          19,
          21,
          22,
          25
        ],
        "placares": [
          12,
          9,
          9,
          10,
          8,
          6,
          11,
          8,
          10,
          9
        ],
        "melhor": 12,
        "media": 9.2,
        "topk": 11.0,
        "alpha_before": 0.39999999999999997,
        "alpha_after": 0.42,
        "ts": "2025-12-02T18:20:43"
      }
    ]
  }
}